[
    {
        "PlayerName": "Jake Burger",
        "Headshot": "https://img.mlbstatic.com/mlb-photos/image/upload/d_people:generic:headshot:silo:current.png/r_max/w_180,q_auto:best/v1/people/669394/headshot/silo/current",
        "Team": "Miami Marlins",
        "OverUnder": "OVER",
        "Line": 1.5,
        "Odds": "+112",
        "HitRate": "8/10"
    },
    {
        "PlayerName": "Isiah Kiner-Falefa",
        "Headshot": "https://img.mlbstatic.com/mlb-photos/image/upload/d_people:generic:headshot:silo:current.png/r_max/w_180,q_auto:best/v1/people/643396/headshot/silo/current",
        "Team": "Pittsburgh Pirates",
        "OverUnder": "UNDER",
        "Line": 1.5,
        "Odds": "-195",
        "HitRate": "8/10"
    },
    {
        "PlayerName": "Aaron Judge",
        "Headshot": "https://img.mlbstatic.com/mlb-photos/image/upload/d_people:generic:headshot:silo:current.png/r_max/w_180,q_auto:best/v1/people/592450/headshot/silo/current",
        "Team": "New York Yankees",
        "OverUnder": "OVER",
        "Line": 1.5,
        "Odds": "-141",
        "HitRate": "9/10"
    },
    {
        "PlayerName": "Gleyber Torres",
        "Headshot": "https://img.mlbstatic.com/mlb-photos/image/upload/d_people:generic:headshot:silo:current.png/r_max/w_180,q_auto:best/v1/people/650402/headshot/silo/current",
        "Team": "New York Yankees",
        "OverUnder": "UNDER",
        "Line": 1.5,
        "Odds": "-157",
        "HitRate": "8/10"
    },
    {
        "PlayerName": "Jake Rogers",
        "Headshot": "https://img.mlbstatic.com/mlb-photos/image/upload/d_people:generic:headshot:silo:current.png/r_max/w_180,q_auto:best/v1/people/668670/headshot/silo/current",
        "Team": "Detroit Tigers",
        "OverUnder": "UNDER",
        "Line": 0.5,
        "Odds": "+120",
        "HitRate": "8/10"
    },
    {
        "PlayerName": "Riley Greene",
        "Headshot": "https://img.mlbstatic.com/mlb-photos/image/upload/d_people:generic:headshot:silo:current.png/r_max/w_180,q_auto:best/v1/people/682985/headshot/silo/current",
        "Team": "Detroit Tigers",
        "OverUnder": "UNDER",
        "Line": 1.5,
        "Odds": "-155",
        "HitRate": "8/10"
    },
    {
        "PlayerName": "Max Schuemann",
        "Headshot": "https://img.mlbstatic.com/mlb-photos/image/upload/d_people:generic:headshot:silo:current.png/r_max/w_180,q_auto:best/v1/people/680474/headshot/silo/current",
        "Team": "Oakland Athletics",
        "OverUnder": "UNDER",
        "Line": 0.5,
        "Odds": "-110",
        "HitRate": "9/10"
    },
    {
        "PlayerName": "Rhys Hoskins",
        "Headshot": "https://img.mlbstatic.com/mlb-photos/image/upload/d_people:generic:headshot:silo:current.png/r_max/w_180,q_auto:best/v1/people/656555/headshot/silo/current",
        "Team": "Milwaukee Brewers",
        "OverUnder": "UNDER",
        "Line": 0.5,
        "Odds": "+110",
        "HitRate": "8/10"
    },
    {
        "PlayerName": "Gary S\u00e1nchez",
        "Headshot": "https://img.mlbstatic.com/mlb-photos/image/upload/d_people:generic:headshot:silo:current.png/r_max/w_180,q_auto:best/v1/people/596142/headshot/silo/current",
        "Team": "Milwaukee Brewers",
        "OverUnder": "OVER",
        "Line": 0.5,
        "Odds": "-180",
        "HitRate": "8/10"
    },
    {
        "PlayerName": "Kyle Schwarber",
        "Headshot": "https://img.mlbstatic.com/mlb-photos/image/upload/d_people:generic:headshot:silo:current.png/r_max/w_180,q_auto:best/v1/people/656941/headshot/silo/current",
        "Team": "Philadelphia Phillies",
        "OverUnder": "UNDER",
        "Line": 1.5,
        "Odds": "-185",
        "HitRate": "9/10"
    },
    {
        "PlayerName": "Josh Rojas",
        "Headshot": "https://img.mlbstatic.com/mlb-photos/image/upload/d_people:generic:headshot:silo:current.png/r_max/w_180,q_auto:best/v1/people/668942/headshot/silo/current",
        "Team": "Seattle Mariners",
        "OverUnder": "UNDER",
        "Line": 0.5,
        "Odds": "-115",
        "HitRate": "8/10"
    },
    {
        "PlayerName": "Tyler Fitzgerald",
        "Headshot": "https://img.mlbstatic.com/mlb-photos/image/upload/d_people:generic:headshot:silo:current.png/r_max/w_180,q_auto:best/v1/people/666149/headshot/silo/current",
        "Team": "San Francisco Giants",
        "OverUnder": "OVER",
        "Line": 0.5,
        "Odds": "-155",
        "HitRate": "8/10"
    },
    {
        "PlayerName": "Austin Martin",
        "Headshot": "https://img.mlbstatic.com/mlb-photos/image/upload/d_people:generic:headshot:silo:current.png/r_max/w_180,q_auto:best/v1/people/668885/headshot/silo/current",
        "Team": "Minnesota Twins",
        "OverUnder": "OVER",
        "Line": 0.5,
        "Odds": "-175",
        "HitRate": "8/10"
    },
    {
        "PlayerName": "Teoscar Hern\u00e1ndez",
        "Headshot": "https://img.mlbstatic.com/mlb-photos/image/upload/d_people:generic:headshot:silo:current.png/r_max/w_180,q_auto:best/v1/people/606192/headshot/silo/current",
        "Team": "Los Angeles Dodgers",
        "OverUnder": "UNDER",
        "Line": 1.5,
        "Odds": "-150",
        "HitRate": "8/10"
    },
    {
        "PlayerName": "Gavin Lux",
        "Headshot": "https://img.mlbstatic.com/mlb-photos/image/upload/d_people:generic:headshot:silo:current.png/r_max/w_180,q_auto:best/v1/people/666158/headshot/silo/current",
        "Team": "Los Angeles Dodgers",
        "OverUnder": "OVER",
        "Line": 0.5,
        "Odds": "-155",
        "HitRate": "8/10"
    },
    {
        "PlayerName": "Steven Kwan",
        "Headshot": "https://img.mlbstatic.com/mlb-photos/image/upload/d_people:generic:headshot:silo:current.png/r_max/w_180,q_auto:best/v1/people/680757/headshot/silo/current",
        "Team": "Cleveland Guardians",
        "OverUnder": "UNDER",
        "Line": 1.5,
        "Odds": "-175",
        "HitRate": "8/10"
    },
    {
        "PlayerName": "Luis Garc\u00eda Jr.",
        "Headshot": "https://img.mlbstatic.com/mlb-photos/image/upload/d_people:generic:headshot:silo:current.png/r_max/w_180,q_auto:best/v1/people/671277/headshot/silo/current",
        "Team": "Washington Nationals",
        "OverUnder": "OVER",
        "Line": 0.5,
        "Odds": "-170",
        "HitRate": "8/10"
    },
    {
        "PlayerName": "Matt Olson",
        "Headshot": "https://img.mlbstatic.com/mlb-photos/image/upload/d_people:generic:headshot:silo:current.png/r_max/w_180,q_auto:best/v1/people/621566/headshot/silo/current",
        "Team": "Atlanta Braves",
        "OverUnder": "UNDER",
        "Line": 1.5,
        "Odds": "-186",
        "HitRate": "8/10"
    },
    {
        "PlayerName": "Michael Harris II",
        "Headshot": "https://img.mlbstatic.com/mlb-photos/image/upload/d_people:generic:headshot:silo:current.png/r_max/w_180,q_auto:best/v1/people/671739/headshot/silo/current",
        "Team": "Atlanta Braves",
        "OverUnder": "UNDER",
        "Line": 1.5,
        "Odds": "-190",
        "HitRate": "8/10"
    }
]