[
    {
        "PlayerName": "Kyle Schwarber",
        "Headshot": "https://img.mlbstatic.com/mlb-photos/image/upload/d_people:generic:headshot:silo:current.png/r_max/w_180,q_auto:best/v1/people/656941/headshot/silo/current",
        "Team": "Philadelphia Phillies",
        "OverUnder": "UNDER",
        "Line": 1.5,
        "Odds": "-165",
        "HitRate": "5/5"
    },
    {
        "PlayerName": "Matt Olson",
        "Headshot": "https://img.mlbstatic.com/mlb-photos/image/upload/d_people:generic:headshot:silo:current.png/r_max/w_180,q_auto:best/v1/people/621566/headshot/silo/current",
        "Team": "Atlanta Braves",
        "OverUnder": "OVER",
        "Line": 1.5,
        "Odds": "+118",
        "HitRate": "5/5"
    },
    {
        "PlayerName": "Cedric Mullins",
        "Headshot": "https://img.mlbstatic.com/mlb-photos/image/upload/d_people:generic:headshot:silo:current.png/r_max/w_180,q_auto:best/v1/people/656775/headshot/silo/current",
        "Team": "Baltimore Orioles",
        "OverUnder": "UNDER",
        "Line": 1.5,
        "Odds": "-175",
        "HitRate": "5/5"
    },
    {
        "PlayerName": "Gunnar Henderson",
        "Headshot": "https://img.mlbstatic.com/mlb-photos/image/upload/d_people:generic:headshot:silo:current.png/r_max/w_180,q_auto:best/v1/people/683002/headshot/silo/current",
        "Team": "Baltimore Orioles",
        "OverUnder": "UNDER",
        "Line": 1.5,
        "Odds": "+100",
        "HitRate": "5/5"
    },
    {
        "PlayerName": "Zach McKinstry",
        "Headshot": "https://img.mlbstatic.com/mlb-photos/image/upload/d_people:generic:headshot:silo:current.png/r_max/w_180,q_auto:best/v1/people/656716/headshot/silo/current",
        "Team": "Detroit Tigers",
        "OverUnder": "OVER",
        "Line": 0.5,
        "Odds": "-180",
        "HitRate": "5/5"
    },
    {
        "PlayerName": "Keibert Ruiz",
        "Headshot": "https://img.mlbstatic.com/mlb-photos/image/upload/d_people:generic:headshot:silo:current.png/r_max/w_180,q_auto:best/v1/people/660688/headshot/silo/current",
        "Team": "Washington Nationals",
        "OverUnder": "UNDER",
        "Line": 1.5,
        "Odds": "-195",
        "HitRate": "5/5"
    },
    {
        "PlayerName": "Ian Happ",
        "Headshot": "https://img.mlbstatic.com/mlb-photos/image/upload/d_people:generic:headshot:silo:current.png/r_max/w_180,q_auto:best/v1/people/664023/headshot/silo/current",
        "Team": "Chicago Cubs",
        "OverUnder": "OVER",
        "Line": 1.5,
        "Odds": "+118",
        "HitRate": "5/5"
    },
    {
        "PlayerName": "Miguel Rojas",
        "Headshot": "https://img.mlbstatic.com/mlb-photos/image/upload/d_people:generic:headshot:silo:current.png/r_max/w_180,q_auto:best/v1/people/500743/headshot/silo/current",
        "Team": "Los Angeles Dodgers",
        "OverUnder": "OVER",
        "Line": 0.5,
        "Odds": "-200",
        "HitRate": "5/5"
    },
    {
        "PlayerName": "Andrew Vaughn",
        "Headshot": "https://img.mlbstatic.com/mlb-photos/image/upload/d_people:generic:headshot:silo:current.png/r_max/w_180,q_auto:best/v1/people/683734/headshot/silo/current",
        "Team": "Chicago White Sox",
        "OverUnder": "UNDER",
        "Line": 1.5,
        "Odds": "-177",
        "HitRate": "5/5"
    },
    {
        "PlayerName": "Luis Robert Jr.",
        "Headshot": "https://img.mlbstatic.com/mlb-photos/image/upload/d_people:generic:headshot:silo:current.png/r_max/w_180,q_auto:best/v1/people/673357/headshot/silo/current",
        "Team": "Chicago White Sox",
        "OverUnder": "UNDER",
        "Line": 1.5,
        "Odds": "-177",
        "HitRate": "5/5"
    },
    {
        "PlayerName": "Yasmani Grandal",
        "Headshot": "https://img.mlbstatic.com/mlb-photos/image/upload/d_people:generic:headshot:silo:current.png/r_max/w_180,q_auto:best/v1/people/518735/headshot/silo/current",
        "Team": "Pittsburgh Pirates",
        "OverUnder": "OVER",
        "Line": 0.5,
        "Odds": "-170",
        "HitRate": "5/5"
    },
    {
        "PlayerName": "Isiah Kiner-Falefa",
        "Headshot": "https://img.mlbstatic.com/mlb-photos/image/upload/d_people:generic:headshot:silo:current.png/r_max/w_180,q_auto:best/v1/people/643396/headshot/silo/current",
        "Team": "Pittsburgh Pirates",
        "OverUnder": "UNDER",
        "Line": 1.5,
        "Odds": "-195",
        "HitRate": "5/5"
    },
    {
        "PlayerName": "Jurickson Profar",
        "Headshot": "https://img.mlbstatic.com/mlb-photos/image/upload/d_people:generic:headshot:silo:current.png/r_max/w_180,q_auto:best/v1/people/595777/headshot/silo/current",
        "Team": "San Diego Padres",
        "OverUnder": "UNDER",
        "Line": 1.5,
        "Odds": "-200",
        "HitRate": "5/5"
    },
    {
        "PlayerName": "Cal Raleigh",
        "Headshot": "https://img.mlbstatic.com/mlb-photos/image/upload/d_people:generic:headshot:silo:current.png/r_max/w_180,q_auto:best/v1/people/663728/headshot/silo/current",
        "Team": "Seattle Mariners",
        "OverUnder": "UNDER",
        "Line": 1.5,
        "Odds": "-137",
        "HitRate": "5/5"
    },
    {
        "PlayerName": "Royce Lewis",
        "Headshot": "https://img.mlbstatic.com/mlb-photos/image/upload/d_people:generic:headshot:silo:current.png/r_max/w_180,q_auto:best/v1/people/668904/headshot/silo/current",
        "Team": "Minnesota Twins",
        "OverUnder": "UNDER",
        "Line": 1.5,
        "Odds": "-139",
        "HitRate": "5/5"
    }
]