[
    {
        "PlayerName": "Noelvi Marte",
        "Headshot": "https://img.mlbstatic.com/mlb-photos/image/upload/d_people:generic:headshot:silo:current.png/r_max/w_180,q_auto:best/v1/people/682622/headshot/silo/current",
        "Team": "Cincinnati Reds",
        "OverUnder": "UNDER",
        "Line": 1.5,
        "Odds": "-175",
        "HitRate": "5/5"
    },
    {
        "PlayerName": "Kyle Schwarber",
        "Headshot": "https://img.mlbstatic.com/mlb-photos/image/upload/d_people:generic:headshot:silo:current.png/r_max/w_180,q_auto:best/v1/people/656941/headshot/silo/current",
        "Team": "Philadelphia Phillies",
        "OverUnder": "UNDER",
        "Line": 1.5,
        "Odds": "-150",
        "HitRate": "5/5"
    },
    {
        "PlayerName": "Brooks Lee",
        "Headshot": "https://img.mlbstatic.com/mlb-photos/image/upload/d_people:generic:headshot:silo:current.png/r_max/w_180,q_auto:best/v1/people/686797/headshot/silo/current",
        "Team": "Minnesota Twins",
        "OverUnder": "OVER",
        "Line": 0.5,
        "Odds": "-185",
        "HitRate": "5/5"
    },
    {
        "PlayerName": "Alex Jackson",
        "Headshot": "https://img.mlbstatic.com/mlb-photos/image/upload/d_people:generic:headshot:silo:current.png/r_max/w_180,q_auto:best/v1/people/656577/headshot/silo/current",
        "Team": "Tampa Bay Rays",
        "OverUnder": "UNDER",
        "Line": 0.5,
        "Odds": "-155",
        "HitRate": "5/5"
    },
    {
        "PlayerName": "JJ Bleday",
        "Headshot": "https://img.mlbstatic.com/mlb-photos/image/upload/d_people:generic:headshot:silo:current.png/r_max/w_180,q_auto:best/v1/people/668709/headshot/silo/current",
        "Team": "Oakland Athletics",
        "OverUnder": "UNDER",
        "Line": 1.5,
        "Odds": "-167",
        "HitRate": "5/5"
    },
    {
        "PlayerName": "Jarren Duran",
        "Headshot": "https://img.mlbstatic.com/mlb-photos/image/upload/d_people:generic:headshot:silo:current.png/r_max/w_180,q_auto:best/v1/people/680776/headshot/silo/current",
        "Team": "Boston Red Sox",
        "OverUnder": "UNDER",
        "Line": 2.5,
        "Odds": "-175",
        "HitRate": "5/5"
    },
    {
        "PlayerName": "Corey Seager",
        "Headshot": "https://img.mlbstatic.com/mlb-photos/image/upload/d_people:generic:headshot:silo:current.png/r_max/w_180,q_auto:best/v1/people/608369/headshot/silo/current",
        "Team": "Texas Rangers",
        "OverUnder": "OVER",
        "Line": 1.5,
        "Odds": "-139",
        "HitRate": "5/5"
    },
    {
        "PlayerName": "Anthony Rendon",
        "Headshot": "https://img.mlbstatic.com/mlb-photos/image/upload/d_people:generic:headshot:silo:current.png/r_max/w_180,q_auto:best/v1/people/543685/headshot/silo/current",
        "Team": "Los Angeles Angels",
        "OverUnder": "OVER",
        "Line": 0.5,
        "Odds": "-185",
        "HitRate": "5/5"
    }
]