[
    {
        "Team1": "New York Yankees",
        "Team2": "Texas Rangers",
        "Total": 8.5
    },
    {
        "Team1": "Pittsburgh Pirates",
        "Team2": "Chicago Cubs",
        "Total": 7.5
    },
    {
        "Team1": "Boston Red Sox",
        "Team2": "New York Mets",
        "Total": 7.5
    },
    {
        "Team1": "Seattle Mariners",
        "Team2": "Oakland Athletics",
        "Total": 7.5
    },
    {
        "Team1": "Minnesota Twins",
        "Team2": "Tampa Bay Rays",
        "Total": 7.5
    },
    {
        "Team1": "Detroit Tigers",
        "Team2": "San Diego Padres",
        "Total": 8
    },
    {
        "Team1": "Los Angeles Dodgers",
        "Team2": "Arizona Diamondbacks",
        "Total": 8.5
    },
    {
        "Team1": "Houston Astros",
        "Team2": "Cincinnati Reds",
        "Total": 9
    },
    {
        "Team1": "Cleveland Guardians",
        "Team2": "Kansas City Royals",
        "Total": 8
    },
    {
        "Team1": "Chicago White Sox",
        "Team2": "Baltimore Orioles",
        "Total": 8.5
    },
    {
        "Team1": "St. Louis Cardinals",
        "Team2": "Milwaukee Brewers",
        "Total": 7.5
    }
]